patchimport.py
patchimport_magic-0.2.0.dist-info/licenses/LICENSE
patchimport_magic-0.2.0.dist-info/METADATA
patchimport_magic-0.2.0.dist-info/WHEEL
patchimport_magic-0.2.0.dist-info/top_level.txt
patchimport_magic-0.2.0.dist-info/RECORD
