Metadata-Version: 2.4
Name: patchimport-magic
Version: 0.2.0
Summary: IPython magic to patch modules before you import them
Author-email: Luigi Finetti <luigi@finetti.com.ar>
License-Expression: BSD-3-Clause
Project-URL: Bug Tracker, https://github.com/dev-random-sas/patchimport-magic/issues
Project-URL: Source Code, https://github.com/dev-random-sas/patchimport-magic
Keywords: ipython,jupyter,magic,import,patch,monkeypatch,hook,testing,benchmarking
Classifier: Development Status :: 4 - Beta
Classifier: Framework :: IPython
Classifier: Intended Audience :: Developers
Classifier: Operating System :: OS Independent
Classifier: Programming Language :: Python
Classifier: Programming Language :: Python :: 3
Classifier: Programming Language :: Python :: 3.9
Classifier: Programming Language :: Python :: 3.10
Classifier: Programming Language :: Python :: 3.11
Classifier: Programming Language :: Python :: 3.12
Classifier: Programming Language :: Python :: 3.13
Classifier: Topic :: Software Development :: Libraries :: Python Modules
Classifier: Topic :: Utilities
License-File: LICENSE
Requires-Dist: ipython>=6.0
Dynamic: license-file
